fddtest/__init__.py
fddtest/fddtest.py
fddtest-0.0.1.dist-info/LICENSE
fddtest-0.0.1.dist-info/METADATA
fddtest-0.0.1.dist-info/WHEEL
fddtest-0.0.1.dist-info/top_level.txt
fddtest-0.0.1.dist-info/RECORD
